pybikes/__init__.py
pybikes/aksu.py
pybikes/ambici.py
pybikes/baksi.py
pybikes/base.py
pybikes/bcycle.py
pybikes/beryl.py
pybikes/bicicard.py
pybikes/bicicas.py
pybikes/bicielx.py
pybikes/biciferrolterra.py
pybikes/bicimad.py
pybikes/bicincitta.py
pybikes/bicing.py
pybikes/bikeshare_ie.py
pybikes/bikeu.py
pybikes/bixi.py
pybikes/bizkaibizi.py
pybikes/careem.py
pybikes/chartered_bike.py
pybikes/clujbike.py
pybikes/compat.py
pybikes/contrib.py
pybikes/cyclocity.py
pybikes/cyclopolis.py
pybikes/cykleo.py
pybikes/data.py
pybikes/decobike.py
pybikes/deutschebahn.py
pybikes/digitransit.py
pybikes/docomo.py
pybikes/easybike.py
pybikes/ecovelo.py
pybikes/emovity.py
pybikes/encicla.py
pybikes/exceptions.py
pybikes/fifteen.py
pybikes/fsm.py
pybikes/ganxeta.py
pybikes/gbfs.py
pybikes/gira.py
pybikes/hellocycling.py
pybikes/joco.py
pybikes/keolis.py
pybikes/kolumbus.py
pybikes/lastenvelo.py
pybikes/linkbike.py
pybikes/meiob.py
pybikes/mobhis.py
pybikes/movus.py
pybikes/nextbike.py
pybikes/nextbike_gbfs.py
pybikes/nubija.py
pybikes/open_source_bike_share.py
pybikes/open_source_bike_share_v2.py
pybikes/openmove.py
pybikes/otp.py
pybikes/ov_fiets.py
pybikes/pedalada.py
pybikes/publibike.py
pybikes/qrobici.py
pybikes/roovee.py
pybikes/samba.py
pybikes/sejong.py
pybikes/seoulbike.py
pybikes/sharedmobility.py
pybikes/slovnaft_bajk.py
pybikes/smartbike.py
pybikes/smoove.py
pybikes/soltrafego.py
pybikes/tashu.py
pybikes/urbansharing.py
pybikes/utils.py
pybikes/velib.py
pybikes/velobike_kz.py
pybikes/velok.py
pybikes/veloway.py
pybikes/weelo.py
pybikes/wegoshare.py
pybikes/xian.py
pybikes/yelovelo.py
pybikes/youbike.py
pybikes/data/aksu.json
pybikes/data/ambici.json
pybikes/data/baksi.json
pybikes/data/bcycle.json
pybikes/data/beryl.json
pybikes/data/bicicard.json
pybikes/data/bicicas.json
pybikes/data/bicielx.json
pybikes/data/biciferrolterra.json
pybikes/data/bicimad.json
pybikes/data/bicincitta.json
pybikes/data/bicing.json
pybikes/data/bikeshare_ie.json
pybikes/data/bikeu.json
pybikes-1.0.7.dist-info/licenses/LICENSE.txt
pybikes-1.0.7.dist-info/METADATA
pybikes-1.0.7.dist-info/WHEEL
pybikes-1.0.7.dist-info/top_level.txt
pybikes-1.0.7.dist-info/RECORD
