Metadata-Version: 2.4
Name: pybikes
Version: 1.0.7
Summary: A python library for scraping bike sharing data
Author-email: Lluis Esquerda <eskerda@gmail.com>
License-Expression: AGPL-3.0
Project-URL: Homepage, https://www.citybik.es
Project-URL: Documentation, https://docs.citybik.es
Project-URL: Source, https://github.com/eskerda/pybikes
Project-URL: Tracker, https://github.com/eskerda/pybikes/issues
Keywords: transport,open data,bike share,bike sharing
Classifier: Development Status :: 4 - Beta
Classifier: Intended Audience :: Developers
Classifier: Intended Audience :: Education
Classifier: Intended Audience :: Science/Research
Classifier: Operating System :: OS Independent
Classifier: Programming Language :: Python
Classifier: Programming Language :: Python :: 3
Classifier: Programming Language :: Python :: 3.9
Classifier: Programming Language :: Python :: 3.10
Classifier: Programming Language :: Python :: 3.11
Classifier: Programming Language :: Python :: 3.12
Classifier: Topic :: Scientific/Engineering
Classifier: Topic :: Scientific/Engineering :: GIS
Requires-Python: >=3.9
License-File: LICENSE.txt
Requires-Dist: requests
Requires-Dist: lxml
Requires-Dist: shapely>=1.5.13
Requires-Dist: importlib_resources; python_version < "3.9"
Requires-Dist: cssselect
Provides-Extra: test
Requires-Dist: pytest; extra == "test"
Requires-Dist: pytest-xdist; extra == "test"
Requires-Dist: gitpython; extra == "test"
Requires-Dist: flake8; extra == "test"
Requires-Dist: jinja2; extra == "test"
Requires-Dist: pytest-metadata==2.0.4; extra == "test"
Requires-Dist: pytest-json-report; extra == "test"
Requires-Dist: python-slugify; extra == "test"
Dynamic: license-file
